fastvector/__init__.py
fastvector/vector.py
fastvector/version.py
fastvector123-5.3.0.dist-info/licenses/LICENSE
fastvector123-5.3.0.dist-info/METADATA
fastvector123-5.3.0.dist-info/WHEEL
fastvector123-5.3.0.dist-info/top_level.txt
fastvector123-5.3.0.dist-info/RECORD
